{"nodes": [{"id": "artifacts_edms_src_hooks_useformdraft_ts", "label": "useFormDraft.ts", "file_type": "code", "source_file": "artifacts\\edms\\src\\hooks\\useFormDraft.ts", "source_location": "L1"}, {"id": "useformdraft_useformdraft", "label": "useFormDraft()", "file_type": "code", "source_file": "artifacts\\edms\\src\\hooks\\useFormDraft.ts", "source_location": "L31"}], "edges": [{"source": "artifacts_edms_src_hooks_useformdraft_ts", "target": "react", "relation": "imports_from", "confidence": "EXTRACTED", "source_file": "artifacts\\edms\\src\\hooks\\useFormDraft.ts", "source_location": "L1", "weight": 1.0}, {"source": "artifacts_edms_src_hooks_useformdraft_ts", "target": "useformdraft_useformdraft", "relation": "contains", "confidence": "EXTRACTED", "source_file": "artifacts\\edms\\src\\hooks\\useFormDraft.ts", "source_location": "L31", "weight": 1.0}], "raw_calls": [{"caller_nid": "useformdraft_useformdraft", "callee": "useState", "source_file": "artifacts\\edms\\src\\hooks\\useFormDraft.ts", "source_location": "L46"}, {"caller_nid": "useformdraft_useformdraft", "callee": "loadSaved", "source_file": "artifacts\\edms\\src\\hooks\\useFormDraft.ts", "source_location": "L47"}, {"caller_nid": "useformdraft_useformdraft", "callee": "useRef", "source_file": "artifacts\\edms\\src\\hooks\\useFormDraft.ts", "source_location": "L53"}, {"caller_nid": "useformdraft_useformdraft", "callee": "useEffect", "source_file": "artifacts\\edms\\src\\hooks\\useFormDraft.ts", "source_location": "L56"}, {"caller_nid": "useformdraft_useformdraft", "callee": "useCallback", "source_file": "artifacts\\edms\\src\\hooks\\useFormDraft.ts", "source_location": "L76"}, {"caller_nid": "useformdraft_useformdraft", "callee": "useCallback", "source_file": "artifacts\\edms\\src\\hooks\\useFormDraft.ts", "source_location": "L84"}, {"caller_nid": "useformdraft_useformdraft", "callee": "useCallback", "source_file": "artifacts\\edms\\src\\hooks\\useFormDraft.ts", "source_location": "L92"}, {"caller_nid": "useformdraft_useformdraft", "callee": "useCallback", "source_file": "artifacts\\edms\\src\\hooks\\useFormDraft.ts", "source_location": "L103"}]}