{"nodes": [{"id": "artifacts_edms_src_components_layout_pagecontainer_tsx", "label": "PageContainer.tsx", "file_type": "code", "source_file": "artifacts\\edms\\src\\components\\layout\\PageContainer.tsx", "source_location": "L1"}, {"id": "pagecontainer_pagecontainer", "label": "PageContainer()", "file_type": "code", "source_file": "artifacts\\edms\\src\\components\\layout\\PageContainer.tsx", "source_location": "L34"}], "edges": [{"source": "artifacts_edms_src_components_layout_pagecontainer_tsx", "target": "react", "relation": "imports_from", "confidence": "EXTRACTED", "source_file": "artifacts\\edms\\src\\components\\layout\\PageContainer.tsx", "source_location": "L1", "weight": 1.0}, {"source": "artifacts_edms_src_components_layout_pagecontainer_tsx", "target": "pagecontainer_pagecontainer", "relation": "contains", "confidence": "EXTRACTED", "source_file": "artifacts\\edms\\src\\components\\layout\\PageContainer.tsx", "source_location": "L34", "weight": 1.0}], "raw_calls": []}